.gitignore
LICENSE
README.md
cefp.py
setup.py
test_cefp.json
test_cefp.py
cefp.egg-info/PKG-INFO
cefp.egg-info/SOURCES.txt
cefp.egg-info/dependency_links.txt
cefp.egg-info/entry_points.txt
cefp.egg-info/top_level.txt