Metadata-Version: 2.1
Name: cefp
Version: 0.0.2
Summary: ArcSight CEF Parser
Home-page: https://github.com/atzm/cefp
Author: Atzm Watanabe
Author-email: atzm@atzm.org
License: BSD-2
Platform: UNKNOWN
Classifier: Development Status :: 3 - Alpha
Classifier: License :: OSI Approved :: BSD License
